{
    "name": "Matt",
    "children": [
                                   {
                                       "name": "Jason",
                                       "parent": "Father",
                                       "children": [
                                                        {
                                                        "name": "Kane"                                                         														
                                                        },
                                                        {
                                                        "name": "Bourne"                                                       
                                                        },													   
													    {
                                                        "name": "Michael"                                                       
                                                        }
                                                   ]
                                   },
     
                                  {
                                       "name": "Alex",
                                       "parent": "Top Node",
									    "children": [
                                                        {
                                                        "name": "Kane"                                                         														
                                                        },
                                                        {
                                                        "name": "Bourne"                                                       
                                                        },													   
													    {
                                                        "name": "Michael"                                                       
                                                        }
                                                   ]
                                  },
								   {
                                       "name": "Micky",
                                       "parent": "Top Node",
									    "children": [
                                                        {
                                                        "name": "Kane"                                                         														
                                                        },
                                                        {
                                                        "name": "Bourne"                                                       
                                                        },													   
													    {
                                                        "name": "Michael"                                                       
                                                        }
                                                   ]
                                  },
								   
                                   {
                                       "name": "Jen",
                                       "parent": "Father",
                                       "children": [
                                                        {
                                                        "name": "Kane"                                                         														
                                                        },
                                                        {
                                                        "name": "Bourne"                                                       
                                                        },													   
													    {
                                                        "name": "Michael"                                                         														
                                                        },
														 {
                                                        "name": "Kane"                                                         														
                                                        },
                                                        {
                                                        "name": "Bourne"                                                       
                                                        },													   
													    {
                                                        "name": "Michael"                                                         														
                                                        },
														 {
                                                        "name": "Kane"                                                         														
                                                        },
                                                        {
                                                        "name": "Bourne"                                                       
                                                        },													   
													    {
                                                        "name": "Michael"                                                         														
                                                        },
														 {
                                                        "name": "Kane"                                                         														
                                                        },
                                                        {
                                                        "name": "Bourne"                                                       
                                                        },													   
													    {
                                                        "name": "Michael"                                                         														
                                                        },
														 {
                                                        "name": "Kane"                                                         														
                                                        },
                                                        {
                                                        "name": "Bourne"                                                       
                                                        },													   
													    {
                                                        "name": "Michael"                                                         														
                                                        }
                                                   ]
                                   }
                ]
 

}